pretix_custom_head/__init__.py
pretix_custom_head/apps.py
pretix_custom_head/models.py
pretix_custom_head/signals.py
pretix_custom_head-0.1.9.dist-info/licenses/LICENSE
pretix_custom_head-0.1.9.dist-info/METADATA
pretix_custom_head-0.1.9.dist-info/WHEEL
pretix_custom_head-0.1.9.dist-info/entry_points.txt
pretix_custom_head-0.1.9.dist-info/top_level.txt
pretix_custom_head-0.1.9.dist-info/RECORD
